nufeb_tools/__init__.py
nufeb_tools/generate_atom.py
nufeb_tools/generate_atom_dev.py
nufeb_tools/maketestplots.py
nufeb_tools/playbook.yml
nufeb_tools/plot.py
nufeb_tools/spatial.py
nufeb_tools/utils.py
nufeb_tools/whole_culture_growth_curves.py
nufeb_tools/templates/__init__.py
nufeb_tools/templates/bacillus.txt
nufeb_tools/templates/fix_bio_kinetics_monod2.txt
nufeb_tools/templates/inputscript.txt
nufeb_tools/templates/local.txt
nufeb_tools/templates/slurm.txt
nufeb_tools/templates/slurm_dev.txt
nufeb_tools-0.1.26.dist-info/AUTHORS.rst
nufeb_tools-0.1.26.dist-info/LICENSE.txt
nufeb_tools-0.1.26.dist-info/METADATA
nufeb_tools-0.1.26.dist-info/WHEEL
nufeb_tools-0.1.26.dist-info/entry_points.txt
nufeb_tools-0.1.26.dist-info/top_level.txt
nufeb_tools-0.1.26.dist-info/RECORD
